tinysession/__init__.py
tinysession_ktalov-1.4.14.dist-info/LICENSE
tinysession_ktalov-1.4.14.dist-info/METADATA
tinysession_ktalov-1.4.14.dist-info/WHEEL
tinysession_ktalov-1.4.14.dist-info/top_level.txt
tinysession_ktalov-1.4.14.dist-info/RECORD
