Metadata-Version: 2.1
Name: tinysession-ktalov
Version: 1.4.14
Summary: A session manager
Home-page: https://gitlab.com/ktalov/tinysession.git
Author: Jose Morales Ventura
Author-email: jomorales.ventura@gmail.com
License: UNKNOWN
Platform: UNKNOWN
Classifier: Programming Language :: Python :: 3
Classifier: License :: OSI Approved :: MIT License
Classifier: Operating System :: OS Independent
Requires-Python: >=3.7
